symlens/__init__.py
symlens/factorize.py
symlens/qe.py
symlens/utils.py
symlens-0.3.3.dist-info/LICENSE
symlens-0.3.3.dist-info/METADATA
symlens-0.3.3.dist-info/WHEEL
symlens-0.3.3.dist-info/top_level.txt
symlens-0.3.3.dist-info/RECORD
