Metadata-Version: 2.1
Name: symlens
Version: 0.3.3
Summary: Symbolic Mode Coupling
Home-page: https://github.com/simonsobs/symlens
Author: Mathew Madhavacheril
Author-email: mathewsyriac@gmail.com
License: BSD license
Keywords: symlens
Platform: UNKNOWN
Classifier: Development Status :: 2 - Pre-Alpha
Classifier: Intended Audience :: Developers
Classifier: License :: OSI Approved :: BSD License
Classifier: Natural Language :: English
Classifier: Programming Language :: Python :: 2
Classifier: Programming Language :: Python :: 2.7
Classifier: Programming Language :: Python :: 3
Classifier: Programming Language :: Python :: 3.4
Classifier: Programming Language :: Python :: 3.5
Classifier: Programming Language :: Python :: 3.6
Classifier: Programming Language :: Python :: 3.7
